my_project/__init__.py
my_project/main.py
my_project/py.typed
test_jfq_project-0.1.8.dist-info/METADATA
test_jfq_project-0.1.8.dist-info/WHEEL
test_jfq_project-0.1.8.dist-info/RECORD
